LICENSE
README.md
setup.cfg
setup.py
coinanalysis/colors.py
coinanalysis/exporter.py
coinanalysis/getQuark.py
coinanalysis/getTransactions.py
coinanalysis/prepareGraph.py
coinanalysis/r_address_list1.py
coinanalysis/r_address_list2.py
coinanalysis/r_address_list3.py
coinanalysis/requester.py
coinanalysis/resource.py
coinanalysis/utils.py
coinanalysis.egg-info/PKG-INFO
coinanalysis.egg-info/SOURCES.txt
coinanalysis.egg-info/dependency_links.txt
coinanalysis.egg-info/requires.txt
coinanalysis.egg-info/top_level.txt