Metadata-Version: 2.1
Name: coinanalysis
Version: 1.0.2
Summary: Coin-help-package For Coin Transaction Analyze.
Home-page: UNKNOWN
Author: Zort Labs
License: Python Script
Platform: UNKNOWN
Provides-Extra: dev
License-File: LICENSE
